confusius/__init__.py
confusius/py.typed
confusius/tests/__init__.py
confusius/tests/test_imports.py
confusius-0.0.1.dist-info/WHEEL
confusius-0.0.1.dist-info/METADATA
confusius-0.0.1.dist-info/RECORD
