Metadata-Version: 2.3
Name: confusius
Version: 0.0.1
Summary: Python package for analysis and visualization of functional ultrasound imaging data.
Author: Samuel Le Meur-Diebolt
Author-email: Samuel Le Meur-Diebolt <samuel@diebolt.io>
Classifier: Development Status :: 2 - Pre-Alpha
Requires-Python: >=3.13
